src/memory/data_mem.sv
module data_mem(
    input logic clk,
    input logic memWrite,
    input logic memRead,
    input logic [31:0] addr,
    input logic [31:0] wd, //write data
    output logic [31:0] rd //readdata
);
    logic [31:0] dmem[0:31];

    initial begin
        $readmemh("testvectors/data.hex", dmem);  // <-- opcional, pode começar vazio
    end

    always_ff @(posedge clk) begin
        if (memWrite)
            dmem[addr >> 2] <= wd;
    end

    assign rd = dmem[addr >> 2];
endmodule

src/core/alu.sv
module alu(
    input logic [31:0] a,
    input logic [31:0] b,
    input logic [2:0] aluControl,
    output logic [31:0] result
);
    always_comb begin
        case (aluControl)
            3'b000: result = a + b;         // ADD
            3'b001: result = a - b;         // SUB
            3'b010: result = a & b;         // AND
            3'b011: result = a | b;         // OR
            3'b100: result = a ^ b;         // XOR
            default: result = 32'd0;
        endcase
    end
endmodule

src/core/regfile.sv
module regfile(
    input logic clk,
    input logic we,
    input logic [4:0] rs1, rs2, rd,
    input logic [31:0] wd,
    output logic [31:0] rd1, rd2
);
    logic [31:0] regs[0:31];

    assign rd1 = regs[rs1];
    assign rd2 = regs[rs2];

    always_ff @(posedge clk) begin
        if (we && rd != 0)
            regs[rd] <= wd;
    end
endmodule

src/core/control_unit.sv
module control_unit(
    input logic [6:0] opcode,
    output logic regWrite,
    output logic aluSrc,
    output logic memRead,
    output logic memWrite,
    output logic [2:0] aluControl
);
    always_comb begin
        regWrite = 0;
        aluSrc = 0;
        memRead = 0;
        memWrite = 0;
        aluControl = 3'b000;

        case (opcode)
            7'b0110011: begin // R-type
                regWrite = 1;
                aluControl = 3'b000;
            end
            7'b0010011: begin // I-type (addi)
                regWrite = 1;
                aluSrc = 1;
                aluControl = 3'b000;
            end
            7'b0000011: begin // LW
                regWrite = 1;
                aluSrc = 1;
                memRead = 1;
                aluControl = 3'b000;
            end
            7'b0100011: begin // SW
                aluSrc = 1;
                memWrite = 1;
                aluControl = 3'b000;
            end
        endcase
    end
endmodule

src/core/immediate_generator.sv
module immediate_generator(
    input logic [31:0] instr,
    output logic [31:0] imm
);
    logic [6:0] opcode;

always @(*) begin
    case (instr[6:0])
        7'b0010011, 7'b0000011: // I-type
            imm = {{20{instr[31]}}, instr[31:20]};
        7'b0100011: // S-type
            imm = {{20{instr[31]}}, instr[31:25], instr[11:7]};
        default:
            imm = 32'd0;
    endcase
end

endmodule

src/memory/instruction_memory.sv
module instruction_memory(
    input logic [31:0] addr,
    output logic [31:0] instr
);
    logic [31:0] imem[0:31];

    initial begin
        $readmemh("testvectors/program.hex", imem);  // <-- Lê o binário das instruções
    end

    assign instr = imem[addr >> 2];  // addr é byte-addressable, por isso >> 2
endmodule

src/core/datapath.sv
module datapath(
    input logic clk,
    input logic reset,
    output logic [31:0] pc,
    output logic [31:0] instr
);
    logic regWrite, aluSrc, memRead, memWrite;
    logic [2:0] aluControl;
    logic [31:0] imm, rd1, rd2, aluB, aluResult, memOut;

    assign pc = pc_reg;
    logic [31:0] pc_reg = 0;

    instruction_memory im(.addr(pc_reg), .instr(instr));
    immediate_generator ig(.instr(instr), .imm(imm));
    control_unit cu(.opcode(instr[6:0]), .*); 
    regfile rf(.clk, .we(regWrite), .rs1(instr[19:15]), .rs2(instr[24:20]),
               .rd(instr[11:7]), .wd(memRead ? memOut : aluResult), .rd1, .rd2);
    alu myalu(.a(rd1), .b(aluSrc ? imm : rd2), .aluControl, .result(aluResult));
    data_mem dm(.clk, .memWrite, .memRead, .addr(aluResult), .wd(rd2), .rd(memOut));

    always_ff @(posedge clk) begin
        pc_reg <= pc_reg + 4;
    end
endmodule

src/top.sv
module top(
    input logic clk,
    input logic reset,
    output logic [31:0] pc,
    output logic [31:0] instr,
    output logic [31:0] cycle
);
    logic [31:0] internal_cycle;

    // Ciclo de clock (contador de ciclos)
    always_ff @(posedge clk) begin
        if (reset)
            internal_cycle <= 0;
        else
            internal_cycle <= internal_cycle + 1;
    end

    assign cycle = internal_cycle;

    // Instância do datapath com pc e instr como saídas
    datapath dp (
        .clk(clk),
        .reset(reset),
        .pc(pc),
        .instr(instr)
    );
endmodule

tb/testbench.sv
module testbench;
    logic clk, reset;
    logic [31:0] pc, instr, cycle;

    // Instância do top
    top uut (
        .clk(clk),
        .reset(reset),
        .pc(pc),
        .instr(instr),
        .cycle(cycle)
    );

    // Geração de clock
    always #5 clk = ~clk; // 10ns por ciclo

    initial begin
        // Inicialização
        clk = 0;
        reset = 1;

        // 🔽 Dump de ondas
        $dumpfile("waveforms/waves.vcd"); // arquivo será salvo na pasta waveforms/
        $dumpvars(0, testbench);          // dump do escopo inteiro a partir de testbench

        // Reset por alguns ciclos
        #20;
        reset = 0;

        // Simulação por alguns ciclos
        repeat (10) begin
            @(posedge clk);
            $display("Cycle = %0d | PC = %0d | instr = %h", cycle, pc, instr);
        end

        $display("Fim da simulação.");
        $finish;
    end
endmodule

waveforms/waves.vcd
$date
	Sun Apr  6 22:02:56 2025
$end
$version
	Icarus Verilog
$end
$timescale
	1s
$end
$scope module testbench $end
$var wire 32 ! pc [31:0] $end
$var wire 32 " instr [31:0] $end
$var wire 32 # cycle [31:0] $end
$var reg 1 $ clk $end
$var reg 1 % reset $end
$scope module uut $end
$var wire 1 $ clk $end
$var wire 32 & cycle [31:0] $end
$var wire 1 % reset $end
$var wire 32 ' pc [31:0] $end
$var wire 32 ( instr [31:0] $end
$var reg 32 ) internal_cycle [31:0] $end
$scope module dp $end
$var wire 1 $ clk $end
$var wire 32 * pc [31:0] $end
$var wire 1 % reset $end
$var wire 1 + regWrite $end
$var wire 32 , rd2 [31:0] $end
$var wire 32 - rd1 [31:0] $end
$var wire 1 . memWrite $end
$var wire 1 / memRead $end
$var wire 32 0 memOut [31:0] $end
$var wire 32 1 instr [31:0] $end
$var wire 32 2 imm [31:0] $end
$var wire 1 3 aluSrc $end
$var wire 32 4 aluResult [31:0] $end
$var wire 3 5 aluControl [2:0] $end
$var reg 32 6 pc_reg [31:0] $end
$scope module cu $end
$var wire 7 7 opcode [6:0] $end
$var reg 3 8 aluControl [2:0] $end
$var reg 1 3 aluSrc $end
$var reg 1 / memRead $end
$var reg 1 . memWrite $end
$var reg 1 + regWrite $end
$upscope $end
$scope module dm $end
$var wire 1 $ clk $end
$var wire 1 / memRead $end
$var wire 1 . memWrite $end
$var wire 32 9 rd [31:0] $end
$var wire 32 : wd [31:0] $end
$var wire 32 ; addr [31:0] $end
$upscope $end
$scope module ig $end
$var wire 32 < instr [31:0] $end
$var reg 32 = imm [31:0] $end
$upscope $end
$scope module im $end
$var wire 32 > addr [31:0] $end
$var wire 32 ? instr [31:0] $end
$upscope $end
$scope module myalu $end
$var wire 3 @ aluControl [2:0] $end
$var wire 32 A b [31:0] $end
$var wire 32 B a [31:0] $end
$var reg 32 C result [31:0] $end
$upscope $end
$scope module rf $end
$var wire 1 $ clk $end
$var wire 5 D rd [4:0] $end
$var wire 32 E rd1 [31:0] $end
$var wire 32 F rd2 [31:0] $end
$var wire 5 G rs1 [4:0] $end
$var wire 5 H rs2 [4:0] $end
$var wire 32 I wd [31:0] $end
$var wire 1 + we $end
$upscope $end
$upscope $end
$upscope $end
$upscope $end
$enddefinitions $end
$comment Show the parameter values. $end
$dumpall
$end
#0
$dumpvars
bx I
b101 H
b0 G
bx F
bx E
b10 D
bx C
bx B
b101 A
b0 @
b10100000000000100010011 ?
b0 >
b101 =
b10100000000000100010011 <
bx ;
bx :
bx 9
b0 8
b10011 7
b0 6
b0 5
bx 4
13
b101 2
b10100000000000100010011 1
bx 0
0/
0.
bx -
bx ,
1+
b0 *
bx )
b10100000000000100010011 (
b0 '
bx &
1%
0$
bx #
b10100000000000100010011 "
b0 !
$end
#5
b1100 A
b11 D
b1100 H
b1100 2
b1100 =
b110000000000000110010011 "
b110000000000000110010011 (
b110000000000000110010011 1
b110000000000000110010011 <
b110000000000000110010011 ?
b100 !
b100 '
b100 *
b100 6
b100 >
b0 #
b0 &
b0 )
1$
#10
0$
#15
b11111111111111111111111111110111 A
b111 D
b10111 H
b11 G
b11111111111111111111111111110111 2
b11111111111111111111111111110111 =
b11111111011100011000001110010011 "
b11111111011100011000001110010011 (
b11111111011100011000001110010011 1
b11111111011100011000001110010011 <
b11111111011100011000001110010011 ?
b1000 !
b1000 '
b1000 *
b1000 6
b1000 >
1$
#20
0$
0%
#25
03
1+
bx A
b100 D
b10 H
b111 G
b110011 7
b0 2
b0 =
b1000111110001000110011 "
b1000111110001000110011 (
b1000111110001000110011 1
b1000111110001000110011 <
b1000111110001000110011 ?
b1100 !
b1100 '
b1100 *
b1100 6
b1100 >
b1 #
b1 &
b1 )
1$
#30
0$
#35
b101 D
b100 H
b11 G
b10000011111001010110011 "
b10000011111001010110011 (
b10000011111001010110011 1
b10000011111001010110011 <
b10000011111001010110011 ?
b10 #
b10 &
b10 )
b10000 !
b10000 '
b10000 *
b10000 6
b10000 >
1$
#40
0$
#45
b101 G
b10000101000001010110011 "
b10000101000001010110011 (
b10000101000001010110011 1
b10000101000001010110011 <
b10000101000001010110011 ?
b10100 !
b10100 '
b10100 *
b10100 6
b10100 >
b11 #
b11 &
b11 )
1$
#50
0$
#55
0+
b10000 D
b111 H
b1100011 7
b10011100101000100001100011 "
b10011100101000100001100011 (
b10011100101000100001100011 1
b10011100101000100001100011 <
b10011100101000100001100011 ?
b100 #
b100 &
b100 )
b11000 !
b11000 '
b11000 *
b11000 6
b11000 >
1$
#60
0$
#65
1+
b100 D
b100 H
b11 G
b110011 7
b10000011010001000110011 "
b10000011010001000110011 (
b10000011010001000110011 1
b10000011010001000110011 <
b10000011010001000110011 ?
b11100 !
b11100 '
b11100 *
b11100 6
b11100 >
b101 #
b101 &
b101 )
1$
#70
0$
#75
0+
b1000 D
b0 H
b100 G
b1100011 7
b100000010001100011 "
b100000010001100011 (
b100000010001100011 1
b100000010001100011 <
b100000010001100011 ?
b110 #
b110 &
b110 )
b100000 !
b100000 '
b100000 *
b100000 6
b100000 >
1$
#80
0$
#85
b0 A
13
1+
b101 D
b0 G
b10011 7
b1010010011 "
b1010010011 (
b1010010011 1
b1010010011 <
b1010010011 ?
b100100 !
b100100 '
b100100 *
b100100 6
b100100 >
b111 #
b111 &
b111 )
1$
#90
0$
#95
bx A
03
1+
b100 D
b10 H
b111 G
b110011 7
b1000111010001000110011 "
b1000111010001000110011 (
b1000111010001000110011 1
b1000111010001000110011 <
b1000111010001000110011 ?
b1000 #
b1000 &
b1000 )
b101000 !
b101000 '
b101000 *
b101000 6
b101000 >
1$
#100
0$
#105
b111 D
b101 H
b100 G
b10100100000001110110011 "
b10100100000001110110011 (
b10100100000001110110011 1
b10100100000001110110011 <
b10100100000001110110011 ?
b101100 !
b101100 '
b101100 *
b101100 6
b101100 >
b1001 #
b1001 &
b1001 )
1$
#110
0$
#115
b10 H
b111 G
b1000000001000111000001110110011 "
b1000000001000111000001110110011 (
b1000000001000111000001110110011 1
b1000000001000111000001110110011 <
b1000000001000111000001110110011 ?
b1010 #
b1010 &
b1010 )
b110000 !
b110000 '
b110000 *
b110000 6
b110000 >
1$
